LICENSE.MD
MANIFEST.in
fibratus.yml
requirements.txt
setup.py
fibratus/__init__.py
fibratus/cli.py
fibratus/common.py
fibratus/config.py
fibratus/context_switch.py
fibratus/controller.py
fibratus/dll.py
fibratus/entrypoint.py
fibratus/errors.py
fibratus/filament.py
fibratus/fs.py
fibratus/handle.py
fibratus/image_meta.py
fibratus/kevent.py
fibratus/kevent_types.py
fibratus/registry.py
fibratus/term.py
fibratus/thread.py
fibratus/version.py
fibratus.egg-info/PKG-INFO
fibratus.egg-info/SOURCES.txt
fibratus.egg-info/dependency_links.txt
fibratus.egg-info/entry_points.txt
fibratus.egg-info/requires.txt
fibratus.egg-info/top_level.txt
fibratus/apidefs/__init__.py
fibratus/apidefs/cdefs.py
fibratus/apidefs/declarer.py
fibratus/apidefs/etw.py
fibratus/apidefs/fs.py
fibratus/apidefs/guiddef.py
fibratus/apidefs/process.py
fibratus/apidefs/registry.py
fibratus/apidefs/sys.py
fibratus/binding/__init__.py
fibratus/binding/base.py
fibratus/binding/yar.py
fibratus/output/__init__.py
fibratus/output/aggregator.py
fibratus/output/amqp.py
fibratus/output/base.py
fibratus/output/console.py
fibratus/output/elasticsearch.py
fibratus/output/fs.py
fibratus/output/smtp.py
fibratus/tcpip/__init__.py
fibratus/tcpip/ports.py
fibratus/tcpip/tcpip.py
filaments/anomalous_process_netio.py
filaments/created_files.py
filaments/elasticsearch_indexing.py
filaments/registry_persistence_detection.py
filaments/top_hives_io.py
filaments/top_in_packets.py
filaments/top_out_packets.py
filaments/top_registry_io_process.py
kstream/__init__.py
kstream/kstreamc.cpp
kstream/kstreamc.pxd
kstream/kstreamc.pyx
kstream/ktuple.pxd
kstream/process.pxd
kstream/time.pxd
kstream/includes/__init__.py
kstream/includes/etw.pxd
kstream/includes/python.pxd
kstream/includes/stdlib.pxd
kstream/includes/string.pxd
kstream/includes/tdh.pxd
kstream/includes/windows.pxd
tests/__init__.py
tests/fixtures/__init__.py
tests/fixtures/filaments/__init__.py
tests/fixtures/filaments/test_filament.py
tests/fixtures/filaments/test_filament_interval.py
tests/fixtures/filaments/test_filament_invalid_interval.py
tests/fixtures/filaments/test_filament_no_on_next_kevent.py
tests/fixtures/filaments/test_filament_nodoc.py
