Metadata-Version: 1.1
Name: fibratus
Version: 0.7.1
Summary: Tool for exploration and tracing of the Windows kernel
Home-page: https://github.com/rabbitstack/fibratus
Author: Nedim Sabic (RabbitStack)
Author-email: bhnedo@hotmail.com
License: Apache
Keywords: windows kernel,tracing,system exploration,syscalls
Platform: Windows
Classifier: Development Status :: 5 - Production/Stable
Classifier: Topic :: System
Classifier: License :: OSI Approved :: Apache Software License
Classifier: Programming Language :: Python :: 3
Classifier: Programming Language :: Python :: 3.2
Classifier: Programming Language :: Python :: 3.3
Classifier: Programming Language :: Python :: 3.4
